singleton2/__init__.py
singleton2/apps.py
singleton2/checks.py
singleton2/conf.py
singleton2/migrations/0001_initial.py
singleton2/migrations/__init__.py
singleton2/models.py
singleton2/urls.py
singleton2/version.py
django_singleton2-0.1.1.dist-info/LICENSE
django_singleton2-0.1.1.dist-info/WHEEL
django_singleton2-0.1.1.dist-info/METADATA
django_singleton2-0.1.1.dist-info/RECORD
