Metadata-Version: 2.1
Name: django-singleton2
Version: 0.1.1
Summary: 
Author: Allyn Treshansky
Author-email: allyn.treshansky@gmail.com
Requires-Python: >=3.8,<4.0
Classifier: Programming Language :: Python :: 3
Classifier: Programming Language :: Python :: 3.8
Classifier: Programming Language :: Python :: 3.9
Classifier: Programming Language :: Python :: 3.10
Classifier: Programming Language :: Python :: 3.11
Requires-Dist: django (>=3.2,<5.0)
Requires-Dist: django-appconf (>=1.0.5,<2.0.0)
Requires-Dist: django-environ (>=0.9.0,<0.10.0)
